Metadata-Version: 1.0
Name: modis-util
Version: 0.1.0
Summary: Modis-util is a tool to make it easy to search and download MODIS data from AWS
Home-page: https://github.com/whistler/modis-util
Author: Ibrahim Muhammad
Author-email: ibmmmm@gmail.com
License: MIT License
